README.md
setup.py
src/__init__.py
src/domainchecker.py
src/domainchecker.egg-info/PKG-INFO
src/domainchecker.egg-info/SOURCES.txt
src/domainchecker.egg-info/dependency_links.txt
src/domainchecker.egg-info/requires.txt
src/domainchecker.egg-info/top_level.txt